apkmod/__init__.py
apkmod/android_manifest_util.py
apkmod/frida_gadget_util.py
apkmod/main.py
apkmod/smali_injector_util.py
apkmod-1.3.0.dist-info/LICENSE
apkmod-1.3.0.dist-info/METADATA
apkmod-1.3.0.dist-info/WHEEL
apkmod-1.3.0.dist-info/entry_points.txt
apkmod-1.3.0.dist-info/top_level.txt
apkmod-1.3.0.dist-info/RECORD
